{
  "planId": "nt_message",
  "day": 336,
  "date": "12-02",
  "title": "메시지 신약 12월 2일 / 사도행전 28:1-16",
  "text": "인원을 점검해 보니 모두가 무사했다. 우리가 있는 곳이 몰타 섬이라는 것을 알았다. \n\n그곳 원주민들이 우리에게 특별히 친절을 베풀어 주었다. 비가 오고 날이 추워서 우리가 흠뻑 젖자 그들은 큰 불을 피우고 그 주위에 우리를 모이게 했다.   \n\n바울도 힘껏 거들기 시작했다. \n\n그가 나뭇가지 한 다발을 모아다가 불에 넣자 불 때문에 깨어난 독사가 그의 손을 물고 놓지 않았다. 원주민들은 바울의 손에 매달린 뱀을 보고 그가 살인자여서 응분의 벌을 받는 것이라고 단정했다. 바울은 손을 털어 뱀을 불 속에 떨어 버렸다. \n\n그는 물리기 전과 다름없이 멀쩡했다. 그들은 그가 급사할 것으로 예상했다가 그런 일이 일어나지 않자 이번에는 그가 신이라고 단정했다!   \n\n그 섬의 지역 추장은 보블리오였다. 그는 우리를 손님으로 자기 집에 맞아들여서 몸도 녹이고 사흘 동안 편히 묵게 해주었다. \n\n마침 보블리오의 아버지가 고열과 이질로 앓아누워 있었다. 바울이 노인의 방에 들어가서 안수하고 기도하자 그의 병이 나았다. 그가 나았다는 소식이 순식간에 퍼졌고 이내 그 섬의 병든 자들이 와서 고침을 받았다.   \n\n로마 \n\n우리는 몰타에서 석 달 동안을 아주 잘 지냈다. 그들은 우리를 극진히 대접해 주었다. 모든 쓸 것을 채워 주고 남은 여정에 필요한 장비까지 챙겨주었다. \n\n그곳 항구에서 겨울을 난 이집트 선박이 이탈리아로 떠날 준비가 되어 우리도 그 배에 올랐다. 그 배의 머리에는 쌍둥이자리, 곧 ‘천상의 쌍둥이’가 조각되어 있었다.   \n\n배는 수라구사에 사흘 동안 정박해 있다가 해안을 따라 레기온으로 올라갔다. 이틀 후에 우리는 남풍을 힘입어 나폴리 만에 입항했다. 거기서 우리는 그리스도인 동료들을 만나 일주일 동안 함께 지냈다.   \n\n그 후에 우리는 로마로 갔다. 로마의 동료들이 우리가 온다는 소식을 듣고 마중을 나왔다. 그 가운데 한 무리는 아피온 광장까지 나왔고 다른 무리는 ‘세 막사’라는 곳에서 우리를 맞았다. \n\n짐작하듯이 그것은 감정을 주체할 수 없는 만남이었다. 바울은 찬양이 흘러넘쳐 감사의 기도로 우리를 인도했다. \n\n우리가 로마에 들어가자 그들은 바울이 그를 지키는 병사와 함께 개인 숙소에서 생활하게 해주었다.  \n\n",
  "audioUrl": null,
  "pageId": "4c88be40-29d8-417d-98ca-cc8b91338472",
  "exportedAt": "2026-06-09T10:08:22.517Z"
}
