{
  "planId": "1year_saehangul",
  "day": 136,
  "date": "05-16",
  "title": "새한글성경 5월 16일 / 시편 54-58편",
  "text": "# 시편 54\n\n어려움에 빠진 사람의 간절한 기도\n\n1찬양 인도자에게 맞춤. 현악기 반주. 마스길(슬기롭게 하는 노래). 다윗에게 속한 것. 시프 사람들이 사울에게 와서 “다윗이 우리 가운데 숨어 있지 않습니까?” 하고 말했을 때.\n\n(기도)\n\n오, 하나님, 주님의 이름으로 나를 구해 주십시오.\n\n주님의 능력으로 내 권리를 찾아 주시기 바랍니다.\n\n2오, 하나님, 내 기도를 들어 주십시오!\n\n내 입의 말에 귀 기울여 주십시오!\n\n3낯선 사람들이 나를 치려고 일어났으니까요.\n\n폭력배들이 내 목숨을 노리니까요.\n\n그들은 하나님을 자신들 앞에 모시지 않습니다. 셀라.\n\n(혼잣말)\n\n4그래, 나를 돕는 분은 하나님이셔.\n\n이 몸을 떠받쳐 주는 분은 주님이셔.\n\n(기도)\n\n5그 나쁜 짓이 나를 적으로 대하는 사람들에게 돌아가게 해 주십시오!\n\n주님의 참되심으로 그들을 다 없애 주십시오.\n\n6기꺼이 내가 주님께 희생제물을 바치겠습니다.\n\n내가 주님의 이름을 찬양하겠습니다,  오, 여호와여,\n\n그렇게 하는 것이 좋으니까요.\n\n(혼잣말)\n\n7온갖 어려움에서 여호와가 나를 건져 내 주셨어.\n\n내 원수들이 망하는 것을 내가 내 눈으로 보고 좋아했지.\n\n# 시편 55\n\n친구에게 배신당한 사람의 탄원\n\n1찬양 인도자에게 맞춤. 현악기 반주. 마스길(슬기롭게 하는 노래). 다윗에게 속한 것.\n\n(기도)\n\n귀 기울여 주십시오, 오, 하나님, 내 기도에!\n\n모르는 체하지 마십시오, 내 탄원을!\n\n2내 말을 주의 깊게 듣고, 내게 대답해 주십시오.\n\n내가 탄식하며 헤매다가 정신을 잃었습니다.\n\n3원수의 소리 때문입니다.\n\n악인의 억누름 때문입니다.\n\n그들이 나를 어려움에 빠뜨리고,\n\n분노하면서 적으로 대하거든요.\n\n4내 심장이 내 안에서 마구 뒤틀리고,\n\n죽음의 공포가 나를 덮쳤습니다.\n\n5두려움과 떨림이 내 안에 들어오고,\n\n무서움이 나를 에워쌌습니다.\n\n6제가 말했지요.\n\n“나에게 비둘기처럼 날개가 있다면!\n\n내가 날아가 쉴 수 있다면!\n\n7저기, 멀리 날아가\n\n광야에 머물 수 있다면!” 셀라.\n\n8어서 나를 위해서 피난처를 찾고 싶습니다,\n\n회오리바람 앞에서, 폭풍 앞에서.\n\n9어지럽게 해 주십시오, 오, 주님, 갈라지게 해 주십시오,\n\n그들의 언어를!\n\n내가 폭력과 다툼을 그 도시 안에서 보았습니다.\n\n10밤낮으로 그런 것들이 성벽 위 곳곳에 있고,\n\n재난과 수고로움이 그 안에 있습니다.\n\n11파멸이 그 안에 있고,\n\n탄압과 거짓이 광장에서 벗어나지 않습니다.\n\n(사람에게 하는 말)\n\n12원수가 아니야, 나를 비아냥거리는 사람은.\n\n그런 건 내가 견뎌 낼 텐데.\n\n나를 미워하는 사람이 아니야, 나에게 건방지게 구는 것은.\n\n그런 사람에게서는 내가 숨을 수 있을 텐데!\n\n13너는 나 자신과도 같은 사람인데,\n\n나의 친구, 나와 친한 사람인데!\n\n14함께 친밀한 사귐을 나누던 사람인데!\n\n하나님의 집에서 우리는 어울려 시끌시끌하게 돌아다녔지.\n\n(혼잣말)\n\n15그들에게 힘든 죽음이 닥치기를!\n\n그들이 산 채로 스올(죽은 사람들의 나라)로 내려가기를!\n\n그들이 머무는 곳에, 그 한가운데 악한 것들이 있기 때문이다.\n\n16나는 하나님께 부르짖고,\n\n여호와는 나를 구해 주실 것이다.\n\n17아침 점심 저녁으로 나는 탄식하며 신음하고,\n\n여호와는 내 소리를 들으실 것이다.\n\n18여호와가 내 목숨을 전쟁에서부터 안전하게 구해 주신다.\n\n무리 가운데 나를 해치려는 사람들이 있기 때문이다.\n\n19하나님은 듣고 그들에게 갚으시는데,\n\n예로부터 임금자리에 앉아 계신 분이시다. 셀라.\n\n그들은 달라지지 않고,\n\n하나님을 두려워하지 않는다.\n\n20내 동무가 손을 펴서 자신의 친구들을 쳤다.\n\n그가 한 약속을 어겼다.\n\n21그의 입은 버터처럼 매끄럽지만,\n\n그의 마음은 전쟁 중이다.\n\n그의 말은 기름보다 부드럽지만,\n\n실제로는 뽑아 든 칼이다.\n\n(사람에게 하는 말)\n\n22여호와께 던져 버리세요, 그대의 짐을!\n\n그러면 여호와가 그대를 돌보아 주실 것입니다.\n\n영원히 내버려두지는 않으실 것입니다, 의인이 흔들리도록.\n\n(기도)\n\n23주님이, 오, 하나님, 그들을 죽음의 구덩이로 끌어 내리십니다.\n\n남의 피를 쏟으며 속임수를 쓰는 사람들은 자기 살날의 절반을 넘기지 못할 것입니다.\n\n그러나 나는, 주님을 의지합니다.\n\n# 시편 56\n\n하나님을 의지하는 사람의 탄원\n\n1찬양 인도자에게 맞춤. 요나텔렘르호킴(멀리 있는 신들에게 날아가는 비둘기) 가락. 다윗에게 속한 것. 믹담. 필리스티아 사람들이 가드에서 그를 붙잡았을 때.\n\n나를 불쌍히 여겨 주십시오, 오, 하나님!\n\n사람이 나를 물고 늘어집니다.\n\n싸움꾼이 온종일 나를 괴롭힙니다.\n\n2나를 적으로 대하는 사람들이 온종일 물고 늘어집니다!\n\n건방지게 나에게 싸움 거는 사람들이 많습니다.\n\n3두려움을 느끼는 날에,\n\n내가, 주님을 의지합니다.\n\n4하나님을 힘입어 나는 하나님의 말씀을 찬양합니다.\n\n하나님을 나는 의지합니다. 나는 두렵지 않습니다.\n\n육신일 뿐인 사람이 내게 무슨 짓을 하겠습니까?\n\n5온종일 내 말을 그들이 문제 삼습니다.\n\n나를 두고서 그들이 세운 모든 계획은 해치려는 것입니다.\n\n6그들은 공격합니다. 숨어서 엿봅니다. 내 발꿈치를 지켜봅니다,\n\n내 목숨을 노리듯이요.\n\n7죄가 있는데도 그들이 살아남을까요?\n\n분노하셔서 백성들을 끌어 내리십시오, 오, 하나님!\n\n8내 비참함을 헤아려 주십시오.\n\n주님이 친히 내 눈물을 주님의 물독에 담아 두십시오.\n\n주님의 두루마리에 적혀 있지 않습니까?\n\n9그때에는 내 원수들이 물러설 것입니다, 내가 부르짖는 날에는.\n\n내가 아는 것은 이것입니다. 나에게는 하나님이 계신다는 사실입니다.\n\n10하나님을 힘입어 나는 말씀을 찬양합니다.\n\n여호와를 힘입어 나는 말씀을 찬양합니다.\n\n11하나님을 나는 의지합니다. 나는 두렵지 않습니다.\n\n사람이 나에게 무슨 짓을 하겠습니까?\n\n12나에게는, 오, 하나님, 주님께 단단히 약속드린 것이 있습니다.\n\n내가 감사제물을 주님께 바치겠습니다.\n\n13주님이 내 목숨을 죽음에서 건져 내 주셨으니까요.\n\n그래서 내 발이 비틀거리지 않고\n\n내가 하나님 앞에서 살아가는 것 아닌가요,\n\n살아 있는 사람들의 빛 가운데서?\n\n# 시편 57\n\n어려움 가운데서 하나님을 찾는 노래\n\n1찬양 인도자에게 맞춤. 알다스헷 가락. 다윗에게 속한 것. 믹담. 그가 사울을 피해 굴속으로 달아날 때.\n\n(기도)\n\n나를 불쌍히 여겨 주십시오, 오, 하나님,\n\n나를 불쌍히 여겨 주십시오!\n\n주님께로 이 몸이 피했고,\n\n주님의 날개 그늘로 내가 피하니까요, 재난이 지나가기까지.\n\n2내가 부르짖습니다, 가장 높으신 하나님께,\n\n나를 위해 나서시는 하나님께.\n\n3하나님은 하늘에서 도움을 보내 나를 구해 주십니다.\n\n나를 물고 늘어지는 사람들을 혼란에 빠뜨리십니다. 셀라.\n\n하나님은 자신의 한결같은 사랑과 진리를 보내십니다.\n\n4이 몸은 사자들 가운데 누워 있습니다.\n\n인간들을 집어삼키는 사자들입니다.\n\n그들의 이빨은 창과 화살이고,\n\n그들의 혀는 날카로운 칼입니다.\n\n5하늘에서 높임받으십시오, 오, 하나님!\n\n온 땅에 주님의 영광이 있습니다.\n\n6그물을 그들이 내 발 앞에 쳤습니다.\n\n이 몸을 내리눌렀습니다.\n\n내 앞에 구덩이를 파 놓았습니다.\n\n그러나 자기들이 그 가운데로 빠졌습니다. 셀라.\n\n7확고합니다, 내 마음은, 오, 하나님! 확고합니다, 내 마음은.\n\n내가 노래하고 찬송하겠습니다.\n\n(악기에게 하는 말)\n\n8깨어라, 내 영광아!\n\n깨어라, 하프와 기타야!\n\n내가 새벽을 깨울 테야!\n\n(기도)\n\n9나 주님께 감사 찬양을 드리겠습니다, 백성들 가운데서, 오, 주님!\n\n나 주님께 찬송하겠습니다, 민족들 가운데서.\n\n10주님의 한결같은 사랑은 커서 하늘에까지 미칩니다,\n\n주님의 참되심은 구름에까지.\n\n11하늘에서 높임받으십시오, 오, 하나님!\n\n온 땅에 주님의 영광이 있습니다.\n\n# 시편 58\n\n악한 권력자들을 벌해 달라는 기도\n\n1찬양 인도자에게 맞춤. 알다스헷 가락. 다윗에게 속한 것. 믹담.\n\n(권력자에게 하는 말)\n\n참으로 침묵이 공의라고 너희는 말하느냐?\n\n올곧게 너희가 인간들을 판가름하고 있느냐?\n\n2세상에서 불의한 짓 할 마음을 너희가 품고,\n\n너희 손으로 폭력을 휘두르는구나.\n\n3악인들은 아기집에서부터 비뚤어졌다.\n\n거짓말쟁이들은 어머니 뱃속에서부터 어그러졌다.\n\n4그들의 독은 뱀의 독 같다.\n\n그들은 자기 귀를 막아 듣지 못하는 살무사 같다.\n\n5이런 살무사는 마술사들의 목소리를 듣지 않는다.\n\n능숙하게 술법을 부려도 듣지 않는다.\n\n(기도)\n\n6오, 하나님, 그들의 입에서 이빨을 부러뜨려 주십시오.\n\n젊은 사자들의 턱뼈를 부서뜨려 주십시오, 오, 여호와여,\n\n7그들이 사라지게 해 주십시오, 흘러가 버리는 물처럼.\n\n화살을 쏘아도 그것들이 꺾여 버린 것처럼 되게 해 주십시오.\n\n8기어가다가 녹아 버리는 달팽이처럼,\n\n죽은 채 태어나 해를 보지 못한 아이처럼 되게 해 주십시오.\n\n(권력자에게 하는 말)\n\n9너희의 솥이 가시나무 땔감으로 달구어지기 전에,\n\n산 것이든 마른 것이든 하나님이 쓸어 가 버리실 것이다.\n\n10의인은 기뻐할 것이다, 보복을 보았으니까.\n\n발을 씻을 것이다, 악인의 피로.\n\n11사람들이 말할 것이다.\n\n“정말 열매가 있구나, 의인에게는.\n\n정말 계시는구나, 세상을 심판하시는 하나님이!”\n\n",
  "audioUrl": null,
  "pageId": "2642693f-9530-4489-8af6-aafba759266a",
  "exportedAt": "2026-06-09T09:34:05.110Z"
}
