{
  "planId": "1year_saehangul",
  "day": 307,
  "date": "11-03",
  "title": "새한글성경 11월 3일 / 시 107-111",
  "text": "# 시편 107\n\n다섯째 권\n\n(시 107-150장)\n\n여호와의 구원을 감사 찬양하는 노래\n\n1“여러분은 여호와께 감사 찬양을 드리세요!\n\n여호와는 좋으시니까요.\n\n영원하니까요, 여호와의 한결같은 사랑은.”\n\n2이렇게 말하기 바랍니다, 여호와께 구원받은 사람들은,\n\n여호와가 적의 손에서 구원해 주신 사람들은!\n\n3여러 지역에서 여호와가 그들을 모아들이셨지요,\n\n동쪽과 서쪽, 북쪽과 바다에서.\n\n4어떤 사람들이 헤맸어요, 빈 들판에서, 거친 들판 길에서.\n\n머물 도시를 찾지 못했어요.\n\n5배고프고 목말라\n\n그들의 기운이 약해졌어요.\n\n6그들이 여호와께 부르짖었어요, 어려움에 빠져서.\n\n괴로움에서 그들을 여호와가 건져 내 주셨어요.\n\n7여호와가 그들을 곧은길로 걸어가게 하셨어요,\n\n그들이 머물 도시로 가도록.\n\n8그들은 여호와께 감사 찬양을 드려야 합니다, 여호와의 한결같은 사랑을 두고서,\n\n그분이 인간들에게 하신 놀라운 일들을 두고서.\n\n9여호와가 목마른 사람에게 물을 실컷 마시게 해 주시고,\n\n배고픈 사람에게 좋은 것을 가득 채워 주셨거든요.\n\n10어떤 사람들은 어둡고 캄캄한 곳에 살지요,\n\n비참하게 쇠사슬에 묶여서.\n\n11그들이 거슬렀거든요, 하나님의 말씀을.\n\n가장 높으신 하나님의 결정을 가볍게 여겼거든요.\n\n12하나님이 수고로 그들의 마음을 낮추셨어요.\n\n그들이 걸려 넘어졌지만 도와주는 사람이 없었어요.\n\n13그들이 여호와께 부르짖었어요, 어려움에 빠져서.\n\n괴로움에서 그들을 여호와가 구해 주셨어요.\n\n14여호와가 끌어내 주셨어요, 그들을 어둡고 캄캄한 데서.\n\n그들의 사슬을 여호와가 끊어 주셨어요.\n\n15그들은 여호와께 감사 찬양을 드려야 합니다, 여호와의 한결같은 사랑을 두고서,\n\n그분이 인간들에게 하신 놀라운 일들을 두고서.\n\n16여호와가 놋문을 깨뜨리시고,\n\n쇠빗장을 잘라 버리셨거든요.\n\n17어떤 사람들은 어수룩해서 자신들의 죄의 길 때문에,\n\n잘못 때문에 괴로움을 불러들였어요.\n\n18어떤 음식도 그들의 목구멍에는 역겨웠어요.\n\n그들은 죽음의 문턱에까지 이르렀어요.\n\n19그들이 여호와께 부르짖었어요, 어려움에 빠져서.\n\n괴로움에서 그들을 여호와가 구해 주셨어요.\n\n20여호와가 자신의 말씀을 보내어 그들을 고쳐 주셨어요.\n\n그들을 구덩이에서 건져 내 주셨어요.\n\n21그들은 여호와께 감사 찬양을 드려야 합니다, 여호와의 한결같은 사랑을 두고서,\n\n그분이 인간들에게 하신 놀라운 일들을 두고서.\n\n22사람들은 감사의 희생제물을 바쳐야 합니다.\n\n여호와가 하신 일을 기쁜 소리로 널리 알려야 합니다.\n\n23어떤 사람들은 배를 타고 바다로 내려갔어요.\n\n넓은 바다에서 일하는 사람들이었어요.\n\n24그들은 직접 보았어요, 여호와가 하신 일들을,\n\n여호와가 하신 놀라운 일들을 깊은 바다에서.\n\n25여호와가 말씀하여 바람을, 폭풍을 일게 하시자,\n\n그 폭풍이 물결을 높이 오르게 했지요.\n\n26그들은 하늘로 올라갔다가\n\n깊은 데로 내려갔어요.\n\n힘들어 혼이 빠져나갔어요.\n\n27그들은 술 취한 사람처럼 흔들려 비틀거렸어요.\n\n그들의 온갖 재주가 쓸모없었어요.\n\n28그들이 여호와께 부르짖었어요, 어려움에 빠져서.\n\n괴로움에서 그들을 여호와가 빼내 주셨어요.\n\n29여호와가 폭풍을 가라앉히시자,\n\n물결이 잔잔해졌지요.\n\n30그들은 기뻐했어요, 바다가 안정되어서.\n\n여호와가 그들을 그들이 가고 싶어 하던 항구로 이끌어 주셨어요.\n\n31그들은 여호와께 감사 찬양을 드려야 합니다, 여호와의 한결같은 사랑을 두고서,\n\n그분이 인간들에게 하신 놀라운 일들을 두고서.\n\n32그들은 여호와를 높여야 합니다, 백성의 모임에서.\n\n원로들이 앉은 자리에서 여호와를 찬양해야 합니다.\n\n33여호와가 강들을 광야로 만드셨어요,\n\n물이 솟는 샘들을 마른땅으로.\n\n34여호와가 열매 맺는 땅을 소금기 있는 땅으로 만드셨습니다.\n\n거기 사는 사람들이 나빴기 때문이지요.\n\n35여호와가 광야를 물웅덩이로 만드셨어요,\n\n메마른 땅을 물이 솟는 샘들로.\n\n36여호와가 굶주린 사람들을 거기 머물게 하시자,\n\n그들은 머물 도시를 세웠지요.\n\n37그들은 밭에 씨를 뿌리고 포도밭을 일구어\n\n거두어들일 열매를 만들어 냈어요.\n\n38여호와가 그들에게 복을 주셔서\n\n크게 번성하게 해 주셨어요.\n\n가축도 줄지 않게 해 주셨고요.\n\n39그러다가 그들의 수가 줄어들고 기가 꺾였지요,\n\n재난과 슬픔에 억눌려서.\n\n40여호와가 멸시를 지체 높은 사람들에게 쏟아부으셨어요.\n\n그들이 길 없는 거친 땅을 헤매게 하셨어요.\n\n41여호와가 가난한 사람을 괴로움에서 지켜 주시고,\n\n그 가문들이 양 떼처럼 많아지게 해 주셨어요.\n\n42올곧은 사람들은 보고 기뻐하지만,\n\n불의한 사람마다 입을 다물지요.\n\n43누가 지혜로운가요? 그는 이런 여러 경우를 살펴보아야 합니다.\n\n깨달아야 합니다, 여호와의 한결같은 사랑을!\n\n# 시편 108\n\n겨레의 적을 물리치게 해 달라는 기도\n\n(시 57:7-11; 60:5-12)\n\n1노래. 노랫말(시). 다윗에게 속한 것.\n\n(기도)\n\n확고합니다, 내 마음은, 오, 하나님!\n\n내가 노래하고 찬송하겠습니다,\n\n내 몸도!\n\n(악기에게 하는 말)\n\n2깨어라, 하프와 기타야!\n\n내가 새벽을 깨울 테야!\n\n(기도)\n\n3나 주님께 감사 찬양을 드리겠습니다, 백성들 가운데서, 오, 여호와여!\n\n나 주님께 찬송하겠습니다, 민족들 가운데서.\n\n4주님의 한결같은 사랑은 커서 하늘 너머에 미칩니다,\n\n주님의 참되심은 구름에까지.\n\n5하늘에서 높임받으십시오, 오, 하나님!\n\n온 땅에 주님의 영광이 있습니다.\n\n6그래서 주님께 사랑받는 사람들이 구조받게 하셨습니다.\n\n주님의 오른손으로 구해 주십시오. 우리에게 대답해 주십시오!\n\n(하나님의 말씀)\n\n7하나님이 하나님의 거룩한곳(성소)에서 말씀하셨습니다.\n\n“내가 기쁨에 겨워할 것이다.\n\n세겜을 나누어서 주고, 숙곳 골짜기도 측량해 볼 것이다.\n\n8길르앗이 내 것, 므낫세가 내 것,\n\n에브라임은 내 머리의 헬멧, 유다는 내 통치 지팡이다.\n\n9모압은 내 세숫대야이다.\n\n에돔에 내가 내 샌들을 던질 것이다.\n\n필리스티아를 두고서는 내가 기뻐 외칠 것이다.”\n\n(기도)\n\n10누가 나를 데려다줄 것입니까, 튼튼하게 만든 도시로?\n\n누가 나를 이끌어다 줄 것입니까, 에돔까지?\n\n11오, 하나님, 주님이 우리를 쫓아내 버리신 것은 아니시지요?\n\n우리 군대와 함께, 오, 하나님, 주님이 나아가지 않으시렵니까?\n\n12어서 우리를 도와 적에게서 벗어나게 해 주십시오.\n\n사람의 도움은 헛됩니다!\n\n(사람에게 하는 말)\n\n13하나님을 힘입어 용감하게 나아갑시다.\n\n하나님이 우리 적들을 짓밟아 버리실 것입니다.\n\n# 시편 109\n\n억울하게 괴로움 겪는 사람의 탄원\n\n1찬양 인도자에게 맞춤. 다윗에게 속한 것. 노랫말(시).\n\n(기도)\n\n내가 찬양하는 하나님, 못 들은 체하지 마십시오.\n\n2사람들이 나를 해치려고 악한 입, 속이는 입을 열었으니까요.\n\n내게 거짓 입술로 말했으니까요.\n\n3미움에 찬 말로, 사람들이 나를 에워쌌습니다.\n\n사람들이 내게 싸움을 걸었습니다, 까닭 없이.\n\n4나는 사랑을 베풀었는데\n\n그들은 나를 적으로 대합니다.\n\n그래도 나는 기도할 뿐입니다.\n\n5그들은 내게 좋은 것을 나쁜 것으로,\n\n내가 베푼 사랑을 미움으로 갚습니다.\n\n6그를 맡아 다룰 악인을 정해 주시고,\n\n맞수가 그의 오른쪽에 서게 해 주십시오.\n\n7재판받을 때 그가 악인으로 드러나게 해 주시고,\n\n그의 기도는 죄로 여겨지게 해 주십시오.\n\n8그의 날들이 짧아지게 해 주십시오.\n\n그가 맡은 일을 다른 사람이 앗아 가게 해 주십시오.\n\n9그의 자식들은 부모 없는 아이들이 되게 해 주시고,\n\n그의 아내는 남편 여읜 여자가 되게 해 주십시오.\n\n10그의 자식들은 반드시 떠돌아다니며 빌어먹게 해 주시고,\n\n쑥대밭이 된 그들의 집에서 쫓겨나게 해 주십시오.\n\n11그에게 있는 모든 것에 빚쟁이가 덫을 놓게 해 주십시오.\n\n그가 벌어들인 것을 낯선 사람들이 빼앗아 가게 해 주십시오.\n\n12그에게는 한결같은 사랑을 베푸는 사람이 없게 해 주십시오.\n\n불쌍히 여기는 사람이 없게 해 주십시오, 그의 부모 없는 자식들에게는.\n\n13그의 후손이 끊어지게 해 주시고,\n\n뒷세대에서는 그들의 이름이 지워지게 해 주십시오.\n\n14그의 조상들의 잘못을 여호와가 기억하시고,\n\n그의 어머니의 죄가 지워지지 않게 해 주십시오.\n\n15잘못과 죄가 여호와 앞에 늘 있게 해 주시고,\n\n그들에 대한 기억이 세상에서 사라지게 해 주십시오.\n\n16그는 기억해 본 적이 없거든요, 한결같은 사랑을 베풀어야 한다는 것을.\n\n오히려 불쌍하고 가난한 사람, 기죽은 사람을 못살게 굴었거든요,\n\n그런 사람을 죽이려고요.\n\n17그가 즐겨 저주했으므로\n\n저주가 그에게 닥치게 해 주십시오.\n\n그가 기꺼이 축복하지 않았으므로\n\n복이 그에게서 멀어지게 해 주십시오.\n\n18그가 저주를 자기의 옷으로 입었으므로\n\n그 저주가 물처럼 그의 창자 속으로,\n\n기름처럼 그의 뼛속으로 들어가게 해 주십시오.\n\n19그 저주가 그에게는 휘감아 두르는 옷처럼 되게 해 주시고,\n\n허리띠로 늘 그것을 그가 띠게 해 주십시오.\n\n20이것이 나를 적으로 대한 사람들이 여호와께로부터 받을 벌입니다.\n\n그들은 이 몸을 두고서 나쁘게 말한 사람들입니다.\n\n21주님이 친히, 오, 여호와여, 나의 주님, 주님의 이름에 걸맞게 나를 다루어 주십시오!\n\n주님의 한결같은 사랑은 좋으니까요. 나를 건져 내 주십시오!\n\n22나는 불쌍하고 가난하니까요.\n\n내 심장이 내 속에서 찔렸습니다.\n\n23길게 드리워진 그림자처럼 나는 사그라졌습니다.\n\n털려 나갔습니다, 메뚜기처럼.\n\n24금식한 탓에 내 무릎이 후들거렸습니다.\n\n기름기가 빠져나가서 내 몸이 야위었습니다.\n\n25나는 그들에게 창핏거리가 되었습니다.\n\n그들이 나를 보고는 머리를 흔듭니다.\n\n26나를 도와주십시오, 오, 여호와 나의 하나님!\n\n나를 구해 주십시오, 주님의 한결같은 사랑으로.\n\n27그들이 알게 해 주십시오, 주님의 손이 이것을 이루셨다는 것을,\n\n주님이, 오, 여호와여, 주님이 그렇게 하셨다는 것을.\n\n28그들은 저주하지만,\n\n주님은 복을 내려 주십니다.\n\n그들은 일어나더라도 부끄러움을 겪고,\n\n주님의 종은 기뻐하게 해 주십시오.\n\n29나를 적으로 대하는 사람들은 수치라는 옷을 입게 해 주십시오.\n\n그들의 부끄러움을 웃옷처럼 몸에 휘감아 두르게 해 주십시오.\n\n(혼잣말)\n\n30나는 크게 감사드릴 테야, 여호와께 내 입으로.\n\n무리 가운데서 여호와를 찬양할 테야.\n\n31여호와는 가난한 사람의 오른쪽에 서 계시거든.\n\n그를 구해 주시거든, 그의 목숨을 두고 판결하는 사람들에게서.\n\n# 시편 110\n\n여호와와 이스라엘의 임금\n\n1다윗에게 속한 것. 노랫말(시).\n\n(시인의 말)\n\n여호와의 말씀입니다, 임금님에게 하신 말씀이지요.\n\n“앉아 있어라, 내 오른쪽에!\n\n내가 그대의 원수들을 그대의 발받침대로 삼을 때까지.”\n\n(임금에게 하는 말)\n\n2임금님의 힘을 드러내는 지팡이를 여호와가 시온에서 보내 주실 것입니다.\n\n임금님은 다스리십시오, 원수들 한가운데서.\n\n3임금님의 백성은 기꺼이 드리는 예물을 가지고 올 것입니다,\n\n임금님이 군대를 부리는 날에.\n\n거룩한 위엄을 갖추고서,\n\n아기집 같은 아침노을 가운데서,\n\n이슬같이 임금님의 젊은이들이 임금님께 나아올 것입니다.\n\n(하나님의 말씀)\n\n4여호와가 굳게 약속하셨으니 거두어들이지 않으실 것입니다.\n\n“그대는 영원히 제사장이야.\n\n멜기세덱의 경우를 따른 것이지.”\n\n(임금에게 하는 말)\n\n5주님이 임금님의 오른쪽 곁에 계십니다.\n\n주님이 분노하시는 날에 임금들을 무찔러 주실 것입니다.\n\n6주님은 민족들에게 책임을 물으실 것입니다.\n\n시체가 가득할 것입니다.\n\n주님이 큰 땅의 우두머리를 무찔러 주실 것입니다.\n\n7임금님은 길에서 냇물을 들이켜실 것입니다.\n\n이런 까닭에 머리를 높이 드실 것입니다.\n\n# 시편 111\n\n놀라운 일들을 하신 여호와 찬양\n\n1할렐루야.\n\n나 여호와께 감사 찬양을 드리려고요, 온 마음으로,\n\n올곧은 사람들의 회의와 백성의 모임에서.\n\n2여호와가 하신 일들이 엄청나지요.\n\n그 일들을 좋아하는 모든 사람이 탐구하지요.\n\n3위엄차고 명예롭지요, 여호와의 활동은.\n\n여호와의 공의는 언제까지나 이어지고요.\n\n4여호와가 기억하게 하셨어요, 자신이 하신 놀라운 일들을.\n\n여호와는 은혜롭고 자비로우시지요.\n\n5먹을 것을 주시지요, 여호와가 자신을 두려워하는 사람들에게.\n\n자신의 언약을 영원히 기억하시고요.\n\n6자신이 하신 일들의 강력함을 나타내 보이셨어요, 여호와가 자신의 백성에게.\n\n그들에게 민족들 몫의 땅을 주시려는 것이지요.\n\n7여호와의 손으로 하신 일들은 참되고 옳지요.\n\n믿을 만하고요, 여호와의 모든 지시는.\n\n8그 지시는 언제까지나 영원히 흔들리지 않아요.\n\n참되고 올곧게 따라야 하지요.\n\n9구원의 손길을 뻗으셨어요, 여호와가 자신의 백성에게.\n\n여호와가 명령하셨지요, 자신이 맺어 주신 언약이 영원하도록.\n\n여호와의 이름은 거룩하고 두려워할 만하고요.\n\n10지혜의 시작은 여호와를 두려워하는 것이지요.\n\n그렇게 하는 모든 사람에게는 훌륭한 분별력이 있고요.\n\n여호와를 찬양하는 것은 언제까지나 이어지지요.\n\n",
  "audioUrl": null,
  "pageId": "77b26650-2c47-42ab-a22a-749fcd7bbf72",
  "exportedAt": "2026-06-09T09:38:24.949Z"
}
