{
  "planId": "nt_saehangul",
  "day": 15,
  "date": "01-15",
  "title": "새한글 신약일독 1월 15일 / 마태복음 10:26-11:1",
  "text": "누구를 두려워해야 할지 말씀하시다\n\n(눅 12:2-7)\n\n26“그러므로 사람들을 두려워하지 마세요. 숨겨 놓은 것치고 들통나지 않을 것이 하나도 없고, 숨겨 둔 것치고 알려지지 않을 것이 없습니다. 27내가 그대들에게 어둠 속에서 말하는 것을 그대들은 빛 가운데서 말하세요. 그대들이 귓속말로 듣는 것을 옥상 위에서 선포하세요. 28몸은 죽이더라도 영혼은 죽일 수 없는 이들을 두려워하지 마세요. 대신 영혼도 몸도 죽여 지옥에 보낼 수 있는 분을 두려워하세요. 29참새 두 마리가 1앗사리온에 팔리지 않나요? 그것들 가운데 하나까지도 그대들의 아버지 모르시게 땅에 떨어지는 일은 없을 겁니다. 30그런데 그대들로 말하자면, 하나님이 머리카락까지도 다 세어 두셨습니다. 31그러므로 두려워하지 마세요. 그대들은 수두룩한 참새하고는 다릅니다, 그대들은요!”\n\n사람들 앞에서 그리스도를 인정하라고 하시다\n\n(눅 12:8-9)\n\n32“그러므로 누구라도 나를 사람들 앞에서 인정한다고 합시다. 그러면 나도 역시 그를 내 아버지, 곧 하늘에 계신 분 앞에서 인정할 겁니다. 33그러나 누구든 사람들 앞에서 나를 인정하지 않는 사람은, 나도 역시 내 아버지, 곧 하늘에 계신 분 앞에서 그를 인정하지 않을 겁니다.”\n\n예수님의 사람이 될 만하려면\n\n(눅 12:51-53; 14:26-27)\n\n34“내가 땅에다 평화를 안겨 주러 왔다고 생각하지 마세요. 평화가 아니라 칼을 안겨 주러 왔습니다. 35나는 갈라놓으러 왔습니다.\n\n사람이 아버지를,\n\n딸이 어머니를,\n\n며느리가 시어머니를 거스르게 하려는 것입니다.\n\n36사람의 원수는 제집 식구들입니다.\n\n37아버지나 어머니를 내 위에 두고 더 사랑하는 사람은, 내 사람이 되기에 알맞지 않습니다. 아들이나 딸을 내 위에 두고 더 사랑하는 사람은, 내 사람이 되기에 알맞지 않습니다. 38자기 십자가를 받아서 메지 않고 내 뒤를 따라오는 사람은 내 사람이 되기에 알맞지 않습니다. 39자기 목숨을 찾으려는 사람은 잃어버릴 것입니다. 그러나 나 때문에 자기 목숨을 잃는 사람은 찾을 것입니다.”\n\n맞아들이는 사람이 받을 보상\n\n(막 9:41)\n\n40“그대들을 맞아들이는 사람은 나를 맞아들이는 것입니다. 나를 맞아들이는 사람은 나를 보내신 분을 맞아들이는 것입니다. 41예언자를 예언자라고 해서 맞아들이는 사람은 예언자의 보상을 받을 것입니다. 의인을 의롭다고 해서 맞아들이는 사람은 의인의 보상을 받을 것입니다. 42오로지 제자라고 해서 이 작은 사람들 가운데 하나에게 시원한 물이라도 한 컵 주어 마시도록 하는 사람이 있다고 합시다. 아멘 그대들에게 말합니다. 그런 사람은 누구든 보상을 절대 잃어버리지 않을 것입니다.”\n\n# 마태복음 11\n\n1예수님이 열두 제자에게 지시하기를 끝마치셨을 때, 거기서 자리를 옮겨 가셨다. 그들의 여러 도시에서 가르치시고 선포하시기 위해서였다.\n\n",
  "audioUrl": null,
  "pageId": "fc52a216-5cf1-4e68-9d62-fb2f3e8e683a",
  "exportedAt": "2026-06-09T09:56:13.685Z"
}
