{
  "planId": "nt_saehangul",
  "day": 80,
  "date": "03-21",
  "title": "새한글 신약일독 3월 21일 / 히브리서 2장",
  "text": "# 히브리서 2\n\n엄청난 구원\n\n1이런 까닭에 우리는 들은 것들에 더더욱 관심을 기울여야만 합니다. 그래서 흘러 떠내려가지 않도록 해야 합니다. 2천사들을 통해서 하신 말씀이 유효하게 되었습니다. 모든 엇나감과 불순종은 마땅한 대가를 받았습니다. 3하물며 우리가, 어떻게 피해 달아나겠습니까? 이렇게 엄청난 구원을 대수롭지 않게 여기고서야 말입니다. 이 구원을 처음에 말씀해 주신 것은 주님이십니다. 그러고는 들은 사람들이 우리한테 이 구원을 믿을 만하다고 굳게 뒷받침해 주었지요. 4하나님도 함께 힘껏 증언해 주셨습니다. 여러 징표와 놀라운 일들과 기적과 또 자신의 뜻을 따라 나눠 주시는 성령님의 선물들로요.\n\n예수님의 낮아지심과 우리의 구원\n\n5장차 올 세상, 곧 우리가 말하고 있는 그 세상을 하나님은 천사들의 지배 아래에 두지 않으셨습니다. 6어디선가 누군가가 힘껏 증언하여 말했습니다.\n\n“사람이 무엇이라고 주님이 그를 기억해 주시며,\n\n인자가 무엇이라고 주님이 그를 돌보아 주십니까?\n\n7주님이 그를 잠시 동안 천사들보다 낮추셨지만,\n\n영광과 명예라는 왕관을 그에게 씌워 주셨습니다.\n\n8모든 것을 그의 발아래에 두셨습니다.”\n\n모든 것을 그의 아래에 두실 때에, 그의 아래에 있지 않은 것은 아무것도 남겨 두지 않으셨습니다. 그러나 지금 우리가 보기에는, 아직까지 모든 것이 그의 아래에 굴복한 것은 아닙니다. 9우리는 잠시 동안 천사들보다 낮아지신 예수님, 그렇지만 죽음의 고난을 통해서 영광과 명예라는 왕관을 쓰고 계신 예수님을 보고 있습니다. 이렇게 예수님은 하나님의 은혜로 모두를 위해 죽음을 맛보셔야 했던 것입니다.\n\n10하나님을 위하여 만물이 생겨났고, 하나님을 통해서 만물이 유지되고 있습니다. 그래서 하나님이 많은 아들딸들을 영광으로 이끌어 들이실 때에, 그들의 구원의 창시자를 고난을 통해 완전하게 하시는 것은 당연한 일입니다. 11거룩하게 해 주시는 분이나 거룩하게 된 사람들이나 모두 한 분한테서 나왔기 때문입니다. 이런 까닭에 예수님은 그들을 형제자매라 부르기를 창피해하지 않으십니다. 12그분은 이렇게 말씀하십니다.\n\n“나 널리 알리겠습니다, 주님의 이름을 내 형제자매들에게.\n\n모임 한가운데서 나 주님을 찬송하겠습니다.”\n\n13또 이렇게도 말씀하십니다.\n\n“나는, 그분을 굳게 믿겠습니다.”\n\n또 이렇게도 말씀하십니다.\n\n“보세요, 나를요, 또 하나님이 내게 주신 자녀들을요.”\n\n14그러므로 자녀들이 다 피와 살을 가진 사람이기 때문에, 예수님 자신도 그들과 똑같이 피와 살을 함께 지니셨습니다. 그것은 자신의 죽음을 통해, 죽음의 힘을 가진 자 곧 마귀를 없애 버리시기 위해서였습니다. 15또 누구든 죽음을 두려워해서, 사는 동안 내내 종살이에서 벗어나지 못하는 사람들을 자유롭게 풀어 주시기 위해서였습니다. 16예수님이 관심 갖고 돌보아 주시는 것은 분명 천사들이 아닙니다. 예수님이 관심 갖고 돌보아 주시는 것은 아브라함의 후손입니다. 17그래서 예수님은 모든 면에서 형제자매들과 같아지셔야 했습니다. 그것은 하나님을 섬기는 일과 관련하여 한결같은 사랑을 품은 믿음직한 대제사장이 되어, 백성의 죗값을 대신 치르시기 위해서였습니다. 18예수님은 몸소 유혹을 받아 고난을 겪어 보신 까닭에, 유혹받는 사람들을 도울 수 있으시니까요.\n\n",
  "audioUrl": null,
  "pageId": "1c7576d9-6adb-80ef-8bed-e1ad4b1410ad",
  "exportedAt": "2026-06-09T09:56:59.390Z"
}
