{
  "planId": "nt_saehangul",
  "day": 287,
  "date": "10-14",
  "title": "새한글 신약일독 10월 14일 / 요한복음 3:1-21",
  "text": "# 요한복음 3\n\n다시 태어남에 대해 니고데모와 말씀을 나누시다\n\n1바리새파에 속한 어떤 사람이 있었다. 그의 이름은 니고데모로, 유대아 사람들의 지도자였다. 2이 사람이 밤에 예수님께로 와서 말했다. “랍비님, 우리가 알기로 랍비님은 하나님께로부터 오신 선생님입니다. 랍비님이 몸소 행하시는 이런 징표들을 아무도 할 수 없기 때문입니다. 하나님이 함께하시지 않으면요.” 3예수님이 그에게 대답하셨다. “아멘 아멘 그대에게 말합니다. 누구든 위로부터 태어나지 않으면 하나님 나라를 볼 수 없습니다.” 4예수님께 니고데모가 말한다. “사람이 나이가 들었는데 어떻게 다시 태어날 수 있습니까? 어머니 뱃속에 또다시 들어갔다가 태어날 수는 없지 않습니까?” 5예수님이 대답하셨다. “아멘 아멘 그대에게 말합니다. 누구든 물과 성령님으로부터 태어나지 않으면 하나님 나라에 들어갈 수 없습니다. 6육신으로부터 태어난 것은 육신이고, 성령님으로부터 태어난 것은 영입니다. 7놀라워하지 마세요, 내가 그대에게 ‘여러분은 위로부터 태어나야만 합니다.’ 하고 말했다고 해서요. 8바람은 불고 싶은 곳에서 불며, 그대는 그 소리를 듣습니다. 그러나 바람이 어디서 오고 어디로 가는지 그대는 알지 못합니다. 성령님으로부터 태어난 사람은 다 이와 같아요.” 9니고데모가 예수님께 대답했다. “이런 일이 어떻게 일어날 수 있습니까?” 10예수님이 그에게 대답하셨다. “그대야말로 이스라엘의 선생인데도 이런 일을 알아듣지 못합니까? 11아멘 아멘 그대에게 말합니다. 우리는 알고 있는 것을 말하고, 본 것을 증언합니다. 그런데 그대들은 우리 증언을 받아들이지 않고 있어요. 12내가 땅의 일을 말했는데도 그대들이 믿지 않고 있는데, 내가 하늘의 일을 말하면 그대들이 어떻게 믿겠습니까?”\n\n예수님을 믿는 사람은 영원한 생명을 얻는다\n\n13“하늘에 올라가 본 사람은 아무도 없어요. 하늘에서 내려온 분, 곧 인자 말고는요. 14모세가 광야에서 뱀을 높이 든 것처럼, 그렇게 인자가 높이 들려야만 합니다. 15그것은 그를 믿는 사람마다 영원한 생명을 누릴 수 있게 하려는 겁니다. 16하나님이 세상을 이처럼 사랑하셔서 하나뿐인 아들을 주셨습니다. 그를 믿는 사람마다 멸망하지 않고 영원한 생명을 누릴 수 있도록 해 주셨습니다. 17하나님이 그 아들을 세상에 보내신 것은 세상을 심판하시려는 것이 아닙니다. 그 아들을 통해서 세상이 구원받게 하시려는 것입니다. 18그를 믿는 사람은 심판받지 않습니다. 그러나 믿지 않는 사람은 이미 심판을 받았습니다. 하나님의 하나뿐인 아들의 이름을 믿지 않았기 때문입니다. 19심판이란 이것입니다. 빛이 세상에 왔는데, 사람들이 빛보다 어두움을 더 사랑했다는 것입니다. 그들이 한 일들이 악했기 때문이지요. 20못된 짓을 하는 사람마다 빛을 미워하고 빛 가까이로 오지 않아요. 자기들이 한 일들이 들추어지지 않게 하려는 것이지요. 21그러나 진리를 실행하는 사람은 빛 가까이로 옵니다. 자기가 한 일들이 하나님 안에서 한 것임이 드러나게 하려는 것이지요.”\n\n",
  "audioUrl": null,
  "pageId": "f61cc87c-ebda-4502-9037-3962b91c6089",
  "exportedAt": "2026-06-09T09:59:27.802Z"
}
