{
  "planId": "nt_saehangul",
  "day": 20,
  "date": "01-20",
  "title": "새한글 신약일독 1월 20일 / 마태복음 13:31-58",
  "text": "겨자씨 비유와 누룩 비유\n\n(막 4:30-32; 눅 13:18-21)\n\n31다른 비유를 그들에게 더 말씀하셨다. “하늘나라는 겨자씨와 같아요. 어떤 남자가 겨자씨를 가져다가 자기 밭에 뿌렸습니다. 32겨자씨는 어떤 씨보다도 작습니다. 그러나 자라난 뒤에는 여느 풀들보다 크게 자라 나무가 됩니다. 그래서 하늘의 새들이 와서 그 가지들에 깃들게 됩니다.”\n\n33다른 비유를 그들에게 말씀하셨다. “하늘나라는 누룩과 같아요. 어떤 여자가 누룩을 가져다가 밀가루 반죽 21리터 속에 섞어 두어서 보이지 않게 했습니다. 그랬더니 마침내 반죽 전체가 부풀어 올랐습니다.”\n\n비유로 말씀하신 까닭을 한 번 더 밝히시다\n\n(막 4:33-34)\n\n34이 모든 것들을 예수님은 비유를 들어 무리들에게 말씀하셨다. 비유를 들지 않고서는 아무것도 그들에게 말씀하지 않으셨다. 35예언자를 통해 하신 말씀을 이루려고 하신 것이었다. 이런 말씀이었다.\n\n“내 입을 열어 비유들을 들려드리지요.\n\n세상의 기초가 놓일 때부터 감추어져 있던 것들을 알려 드리지요.”\n\n독보리 비유를 설명해 주시다\n\n36그때에 예수님이 무리들을 남겨 두고 집으로 가셨다. 그러자 제자들이 예수님께 다가와 말씀드렸다. “밭의 독보리 비유를 저희에게 쉽게 설명해 주세요.” 37예수님이 대답하셨다. “좋은 씨를 뿌리는 사람은 인자를 말합니다. 38밭은 세상을 말합니다. 좋은 씨는 이 사람들, 곧 그 나라의 아들딸들을 말합니다. 독보리는 악의 아들딸들을 말합니다. 39독보리를 뿌려 놓은 원수는 마귀를 말합니다. 수확은 세대의 끝을 말합니다. 수확꾼들은 천사들을 말합니다. 40그러므로 독보리가 한데 뽑혀 모조리 불에 태워지듯이, 세상이 끝날 때에도 그럴 것입니다. 41인자가 자기 천사들을 보낼 겁니다. 그리고 걸려 넘어지게 하는 모든 것들과 불법을 저지르는 사람들을, 천사들이 그의 나라에서 뽑아 모을 겁니다. 42그러고는 그들을 불구덩이에 던져 넣을 것입니다. 거기서 그들은 울부짖으며 이를 갈 것입니다. 43그때에 정의로운 사람들은 자기들의 아버지 나라에서 해처럼 환히 빛날 것입니다. 귀 있는 사람은 들으시기 바랍니다.”\n\n세 가지 비유\n\n44“하늘나라는 밭에 감추어져 있는 보물과 같습니다. 어떤 사람이 그 보물을 발견하고는 그대로 감추어 두었어요. 그러고는 기뻐하며 가서, 가진 것을 모두 다 팔아 그 밭을 삽니다.\n\n45또 하늘나라는 좋은 진주들을 찾고 있는 상인의 경우와도 같아요. 46값나가는 진주 하나를 발견하고는, 가서 가진 것을 모두 다 팔아서 그 진주를 샀습니다.\n\n47또 하늘나라는 바다에 던져져 온갖 종류의 물고기를 모아들이는 그물의 경우와 같아요. 48그물이 가득 찼을 때 사람들이 그물을 해변으로 끌어 올렸습니다. 그리고 앉아서 좋은 것들은 골라 모아서 그릇에 담고, 형편없는 것들은 바깥에 버렸어요. 49세대 끝에도 그럴 겁니다. 천사들이 나가서 정의로운 사람들 가운데서 악한 사람들을 따로 추려 낼 겁니다. 50그러고는 그들을 불구덩이에 던져 넣을 것입니다. 거기서 그들은 울부짖으며 이를 갈 것입니다.”\n\n하늘나라의 제자가 된 율법학자의 비유\n\n51“그대들은 이것들을 다 이해했나요?” 그들이 예수님께 “예.” 하고 대답한다. 52예수님이 그들에게 말씀하셨다. “이런 까닭에 하늘나라의 제자가 된 율법학자마다 집주인과 같아요. 그는 자기 창고에서 새것과 옛것을 꺼내 놓습니다.”\n\n고향에서 환영받지 못하시다\n\n(막 6:1-6; 눅 4:16-30)\n\n53예수님이 이런 비유들을 끝마치셨을 때, 거기서 떠나가셨다. 54그리고 자기 고향 마을로 가셔서 그들의 회당에서 사람들을 가르치고 계셨다. 사람들이 몹시 놀라 말했다. “이 사람은 어디서 이런 지혜와 놀라운 능력을 얻게 된 거지? 55이 사람, 목수 아들이잖아? 어머니는 마리아라고들 하지 않나? 그의 형제들은 야고보와 요셉과 시몬과 유다가 아닌가? 56그의 누이들이 모두 우리 곁에 있잖아? 도대체 이 사람이 어디서 이런 모든 것을 얻게 된 거지?” 57이렇게 예수님 때문에 사람들이 걸려 넘어지고 있었다. 그러자 예수님이 그들에게 말씀하셨다. “예언자가 존중받지 못하는 경우가 없습니다. 고향과 자기 집에서 말고는요.” 58그리고 거기서는 능력을 내보이는 놀라운 일들을 많이 하지 않으셨다. 고향 사람들이 믿지 않아서였다.\n\n",
  "audioUrl": null,
  "pageId": "c92fad86-da0e-4e91-9c47-4806aa0d23ca",
  "exportedAt": "2026-06-09T09:56:17.429Z"
}
